slothy/__init__.py
slothy/_importing.py
slothy/py.typed
slothy-1.0.0.dist-info/LICENSE
slothy-1.0.0.dist-info/METADATA
slothy-1.0.0.dist-info/WHEEL
slothy-1.0.0.dist-info/RECORD
