Metadata-Version: 2.1
Name: slothy
Version: 1.0.0
Summary: Super-easy lazy importing in Python.
Home-page: https://github.com/bswck/slothy
License: MIT
Author: bswck
Author-email: bartoszpiotrslawecki@gmail.com
Requires-Python: >=3.8
Classifier: License :: OSI Approved :: MIT License
Classifier: Programming Language :: Python :: 3
Classifier: Programming Language :: Python :: 3.8
Classifier: Programming Language :: Python :: 3.9
Classifier: Programming Language :: Python :: 3.10
Classifier: Programming Language :: Python :: 3.11
Classifier: Programming Language :: Python :: 3.12
Project-URL: Coverage, https://coverage-badge.samuelcolvin.workers.dev/redirect/bswck/slothy
Project-URL: Documentation, https://slothy.readthedocs.io/en/latest/
Project-URL: Distribution, https://pypi.org/project/slothy/
Project-URL: Issues, https://github.com/bswck/slothy/issues
